mdconv/__init__.py
mdconv/parse.py
mdconv/parse_test.py
mdlang/__init__.py
mdlang/syntax.py
mdlang/syntax_test.py
pychar/None.py
pychar/__init__.py
mdconv-0.1.3.dist-info/METADATA
mdconv-0.1.3.dist-info/WHEEL
mdconv-0.1.3.dist-info/top_level.txt
mdconv-0.1.3.dist-info/RECORD
